higis_tools/__init__.py
higis_tools/serverless.py
higis_tools/setup.py
higis_tools-1.0.2.dist-info/METADATA
higis_tools-1.0.2.dist-info/WHEEL
higis_tools-1.0.2.dist-info/top_level.txt
higis_tools-1.0.2.dist-info/RECORD
